{
  "IMGL0383-Enhanced-NR.jpg": {
    "name": "IMGL0383-Enhanced-NR.jpg",
    "rating": null,
    "sha1": "29cc67d309db51225fd976848b8fd904a6e41583",
    "size": 7936422,
    "small_url": "https://hollings-photography-site.s3.us-west-1.amazonaws.com/small/IMGL0383-Enhanced-NR.jpg",
    "thumbnail_url": "https://hollings-photography-site.s3.us-west-1.amazonaws.com/thumb/IMGL0383-Enhanced-NR.jpg",
    "url": "https://hollings-photography-site.s3.us-west-1.amazonaws.com/IMGL0383-Enhanced-NR.jpg"
  }
}